Face_Mash.py
Face_Mash-127.0.0.0.dist-info/LICENSE
Face_Mash-127.0.0.0.dist-info/METADATA
Face_Mash-127.0.0.0.dist-info/WHEEL
Face_Mash-127.0.0.0.dist-info/top_level.txt
Face_Mash-127.0.0.0.dist-info/RECORD
