Metadata-Version: 2.1
Name: Face-Mash
Version: 127.0.0.0
Summary: Deep Learning model for fatigue detection
Author: Murali,Monica
Keywords: deep learning,drowsiness detection,fatigue analysis
Classifier: Programming Language :: Python :: 3
Classifier: License :: OSI Approved :: MIT License
Classifier: Operating System :: OS Independent
Requires-Python: >=3.6
License-File: LICENSE
Requires-Dist: keras >=2.6.0
Requires-Dist: opencv-python >=4.5.3
Requires-Dist: numpy >=1.19.5
Requires-Dist: tensorflow >=2.13.0
Requires-Dist: gdown >=4.7.1
